gpyconform/__init__.py
gpyconform/exact_gpcp.py
gpyconform/exact_prediction_strategies_cp.py
gpyconform/prediction_intervals.py
gpyconform-0.1.1.dist-info/LICENSE.txt
gpyconform-0.1.1.dist-info/METADATA
gpyconform-0.1.1.dist-info/WHEEL
gpyconform-0.1.1.dist-info/top_level.txt
gpyconform-0.1.1.dist-info/RECORD
