Metadata-Version: 2.1
Name: gpyconform
Version: 0.1.1
Summary: Extends GPyTorch with Gaussian Process Regression Conformal Prediction
Home-page: https://github.com/harrisp/GPyConform
Author: Harris Papadopoulos
Author-email: h.papadopoulos@frederick.ac.cy
Project-URL: Bug Tracker, https://github.com/harrisp/GPyConform/issues
Project-URL: Documentation, https://gpyconform.readthedocs.io
Keywords: Gaussian Process Regression,Conformal Prediction,Prediction Regions,Prediction Intervals,Uncertainty Quantification,Coverage Guarantee,Normalized Nonconformity
Classifier: Programming Language :: Python :: 3
Classifier: License :: OSI Approved :: BSD License
Classifier: Operating System :: OS Independent
Requires-Python: >=3.8
License-File: LICENSE.txt
Requires-Dist: gpytorch==1.13
Requires-Dist: torch>=2.0
Requires-Dist: linear_operator>=0.5.3
Requires-Dist: numpy
